{"1": {"11": [], "10": [], "12": [], "1": ["\u65c5\u6e38\u4fe1\u606f\u5316"], "3": ["\u4f11\u95f2\u6982\u8bba"], "2": ["\u65c5\u6e38\u4fe1\u606f\u5316"], "5": ["\u65c5\u884c\u793e\u7ecf\u8425\u7ba1\u7406\u4e0e\u5b9e\u8df5"], "4": ["\u4f11\u95f2\u6982\u8bba"], "7": [], "6": ["\u65c5\u884c\u793e\u7ecf\u8425\u7ba1\u7406\u4e0e\u5b9e\u8df5"], "9": [], "8": []}, "3": {"11": [], "10": ["\u751f\u6001\u5b89\u5168\u4e0e\u73af\u5883\u5065\u5eb7"], "12": [], "1": [], "3": ["\u65c5\u6e38\u666f\u533a\u7ecf\u8425\u4e0e\u7ba1\u7406"], "2": [], "5": [], "4": ["\u65c5\u6e38\u666f\u533a\u7ecf\u8425\u4e0e\u7ba1\u7406"], "7": [], "6": [], "9": ["\u751f\u6001\u5b89\u5168\u4e0e\u73af\u5883\u5065\u5eb7"], "8": []}, "2": {"11": [], "10": [], "12": [], "1": ["\u57fa\u7840\u82f1\u8bed2-2"], "3": ["\u57fa\u7840\u82f1\u8bed2-2"], "2": ["\u57fa\u7840\u82f1\u8bed2-2"], "5": ["\u8d22\u52a1\u4e0e\u4f1a\u8ba1"], "4": ["\u57fa\u7840\u82f1\u8bed2-2"], "7": [], "6": ["\u8d22\u52a1\u4e0e\u4f1a\u8ba1"], "9": [], "8": []}, "5": {"11": [], "10": [], "12": [], "1": ["\u65c5\u6e38\u89c4\u5212"], "3": ["\u4eba\u529b\u8d44\u6e90\u7ba1\u7406"], "2": ["\u65c5\u6e38\u89c4\u5212"], "5": [], "4": ["\u4eba\u529b\u8d44\u6e90\u7ba1\u7406"], "7": [], "6": [], "9": [], "8": []}, "4": {"11": [], "10": [], "12": [], "1": ["\u57fa\u7840\u82f1\u8bed2-2"], "3": ["\u57fa\u7840\u82f1\u8bed2-2"], "2": ["\u57fa\u7840\u82f1\u8bed2-2"], "5": ["\u65c5\u6e38\u76ee\u7684\u5730\u8425\u9500"], "4": ["\u57fa\u7840\u82f1\u8bed2-2"], "7": [], "6": ["\u65c5\u6e38\u76ee\u7684\u5730\u8425\u9500"], "9": [], "8": []}, "7": {"11": [], "10": [], "12": [], "1": [], "3": [], "2": [], "5": [], "4": [], "7": [], "6": [], "9": [], "8": []}, "6": {"11": [], "10": [], "12": [], "1": [], "3": [], "2": [], "5": [], "4": [], "7": [], "6": [], "9": [], "8": []}}