{"1": {"11": [], "10": ["\u524d\u8fdb\u4e2d\u7684\u7269\u7406\u5b66\u4e0e\u4eba\u7c7b\u6587\u660e"], "12": [], "1": [], "3": [], "2": [], "5": ["\u4e2d\u56fd\u519c\u6751\u653f\u6cbb\u5b66"], "4": [], "7": ["\u5f53\u4ee3\u65e5\u672c\u653f\u5e9c\u4e0e\u653f\u6cbb"], "6": ["\u4e2d\u56fd\u519c\u6751\u653f\u6cbb\u5b66"], "9": ["\u524d\u8fdb\u4e2d\u7684\u7269\u7406\u5b66\u4e0e\u4eba\u7c7b\u6587\u660e"], "8": ["\u5f53\u4ee3\u65e5\u672c\u653f\u5e9c\u4e0e\u653f\u6cbb"]}, "3": {"11": [], "10": ["\u7ebf\u6027\u4ee3\u6570"], "12": [], "1": [], "3": ["\u751f\u6001\u5b66\u57fa\u7840"], "2": [], "5": ["\u9a6c\u514b\u601d\u4e3b\u4e49\u57fa\u672c\u539f\u7406\u4e13\u9898"], "4": ["\u751f\u6001\u5b66\u57fa\u7840"], "7": ["\u9a6c\u514b\u601d\u4e3b\u4e49\u57fa\u672c\u539f\u7406\u4e13\u9898"], "6": ["\u9a6c\u514b\u601d\u4e3b\u4e49\u57fa\u672c\u539f\u7406\u4e13\u9898"], "9": ["\u7ebf\u6027\u4ee3\u6570"], "8": ["\u9a6c\u514b\u601d\u4e3b\u4e49\u57fa\u672c\u539f\u7406\u4e13\u9898"]}, "2": {"11": [], "10": [], "12": [], "1": [], "3": ["\u4eea\u5668\u5206\u6790"], "2": [], "5": ["\u4e9a\u592a\u5730\u533a\u653f\u6cbb\u4e0e\u7ecf\u6d4e"], "4": ["\u4eea\u5668\u5206\u6790"], "7": ["\u4e9a\u592a\u5730\u533a\u653f\u6cbb\u4e0e\u7ecf\u6d4e"], "6": ["\u4e9a\u592a\u5730\u533a\u653f\u6cbb\u4e0e\u7ecf\u6d4e"], "9": [], "8": []}, "5": {"11": [], "10": [], "12": [], "1": ["\u65cf\u7fa4\u4e0e\u653f\u6cbb\u53d1\u5c55"], "3": ["\u516c\u5171\u5173\u7cfb\u5b66"], "2": ["\u65cf\u7fa4\u4e0e\u653f\u6cbb\u53d1\u5c55"], "5": ["\u73af\u5883\u5fae\u751f\u7269\u5b66"], "4": ["\u516c\u5171\u5173\u7cfb\u5b66"], "7": ["\u73af\u5883\u5fae\u751f\u7269\u5b66"], "6": ["\u73af\u5883\u5fae\u751f\u7269\u5b66"], "9": [], "8": []}, "4": {"11": [], "10": ["\u73af\u5883\u4e0e\u5065\u5eb7"], "12": [], "1": ["\u4e16\u8d38\u7ec4\u7ec7\u6cd5"], "3": ["\u7f51\u7edc\u5316\u5b66\u8d44\u6e90"], "2": ["\u4e16\u8d38\u7ec4\u7ec7\u6cd5"], "5": [], "4": ["\u7f51\u7edc\u5316\u5b66\u8d44\u6e90"], "7": ["\u6982\u7387\u8bba\u4e0e\u6570\u7406\u7edf\u8ba1"], "6": [], "9": ["\u73af\u5883\u4e0e\u5065\u5eb7"], "8": ["\u6982\u7387\u8bba\u4e0e\u6570\u7406\u7edf\u8ba1"]}, "7": {"11": [], "10": [], "12": [], "1": [], "3": [], "2": [], "5": [], "4": [], "7": [], "6": [], "9": [], "8": []}, "6": {"11": [], "10": [], "12": [], "1": [], "3": [], "2": [], "5": [], "4": [], "7": [], "6": [], "9": [], "8": []}}